{
  "$schema": "https://raw.githubusercontent.com/dineug/erd-editor/main/json-schema/schema.json",
  "version": "3.0.0",
  "settings": {
    "width": 2000,
    "height": 2000,
    "scrollTop": -13,
    "scrollLeft": 0,
    "zoomLevel": 1,
    "show": 431,
    "database": 16,
    "databaseName": "",
    "canvasType": "ERD",
    "language": 1,
    "tableNameCase": 4,
    "columnNameCase": 2,
    "bracketType": 1,
    "relationshipDataTypeSync": true,
    "relationshipOptimization": false,
    "columnOrder": [
      1,
      2,
      4,
      8,
      16,
      32,
      64
    ],
    "maxWidthComment": -1,
    "ignoreSaveSettings": 0
  },
  "doc": {
    "tableIds": [
      "OHUwIk3akz95xyDa54ouD",
      "mZHhCYR1X1U1gUz2KWHw5",
      "xYQg6fdK8K6X4smH_AEEd",
      "HeguguGg0Aurg_X0m8aun",
      "SWR1nBjuriuWRbCNOJ9-8",
      "fA5YAi6m7r_7Jq-6dO6In",
      "wFQyrIndy8OPPc_ww1_zJ"
    ],
    "relationshipIds": [
      "HrhjzYRmn4BteqTXRRN6U",
      "D4k-smELvxhynQASujH8f",
      "esEsOG2cEPwgDGCr8Ocl-",
      "fUM9GdfcLQrUJvGxaCIe3",
      "t0DA6SoiX-EPclq0fFaVW",
      "JIumuo9Fx7Ba-cwTTJRq7"
    ],
    "indexIds": [],
    "memoIds": []
  },
  "collections": {
    "tableEntities": {
      "OHUwIk3akz95xyDa54ouD": {
        "id": "OHUwIk3akz95xyDa54ouD",
        "name": "Company",
        "comment": "",
        "columnIds": [
          "nYG4SyWmCAYP5N2vPAz_6",
          "Ho3945r3JY8Y5r3w2TP2H"
        ],
        "seqColumnIds": [
          "4Zxvx0s8Leiigsb9hDuDh",
          "nYG4SyWmCAYP5N2vPAz_6",
          "Ho3945r3JY8Y5r3w2TP2H"
        ],
        "ui": {
          "x": 3,
          "y": 130,
          "zIndex": 2,
          "widthName": 60,
          "widthComment": 60,
          "color": ""
        },
        "meta": {
          "updateAt": 1729454768061,
          "createAt": 1729453796998
        }
      },
      "mZHhCYR1X1U1gUz2KWHw5": {
        "id": "mZHhCYR1X1U1gUz2KWHw5",
        "name": "Brand",
        "comment": "",
        "columnIds": [
          "Lim_plEDkYq8hh62avnjz",
          "v8xIZyNHCENlP30ZhysHp"
        ],
        "seqColumnIds": [
          "Lim_plEDkYq8hh62avnjz",
          "v8xIZyNHCENlP30ZhysHp"
        ],
        "ui": {
          "x": 3,
          "y": 242,
          "zIndex": 48,
          "widthName": 60,
          "widthComment": 60,
          "color": ""
        },
        "meta": {
          "updateAt": 1729455043826,
          "createAt": 1729453905773
        }
      },
      "xYQg6fdK8K6X4smH_AEEd": {
        "id": "xYQg6fdK8K6X4smH_AEEd",
        "name": "Primary Category",
        "comment": "",
        "columnIds": [
          "1ZSgi6DeMk-Jho5R_QizO",
          "8VerGkGgP1UH8UePAsKmT",
          "kMzuUBPZRJC61024hUJMZ"
        ],
        "seqColumnIds": [
          "1ZSgi6DeMk-Jho5R_QizO",
          "8VerGkGgP1UH8UePAsKmT",
          "kMzuUBPZRJC61024hUJMZ"
        ],
        "ui": {
          "x": 4,
          "y": 351,
          "zIndex": 68,
          "widthName": 93,
          "widthComment": 60,
          "color": ""
        },
        "meta": {
          "updateAt": 1729455047229,
          "createAt": 1729453944353
        }
      },
      "HeguguGg0Aurg_X0m8aun": {
        "id": "HeguguGg0Aurg_X0m8aun",
        "name": "Sub Category",
        "comment": "",
        "columnIds": [
          "MhCRw0EByiT4XV9QFQoTx",
          "5prYfpdXY5jtGTO0sioHA",
          "VCH2_6zYiyzTp7HXJP9Lk"
        ],
        "seqColumnIds": [
          "MhCRw0EByiT4XV9QFQoTx",
          "5prYfpdXY5jtGTO0sioHA",
          "VCH2_6zYiyzTp7HXJP9Lk"
        ],
        "ui": {
          "x": 5,
          "y": 485,
          "zIndex": 107,
          "widthName": 73,
          "widthComment": 60,
          "color": ""
        },
        "meta": {
          "updateAt": 1729455049413,
          "createAt": 1729454099543
        }
      },
      "SWR1nBjuriuWRbCNOJ9-8": {
        "id": "SWR1nBjuriuWRbCNOJ9-8",
        "name": "Chemical",
        "comment": "",
        "columnIds": [
          "3ODW-TsDOXhFcTLejp6qx",
          "LLvedpn18Oz5ddhrOt86g"
        ],
        "seqColumnIds": [
          "ey9Qcpf5S6aTwinQ8-m_j",
          "3ODW-TsDOXhFcTLejp6qx",
          "LLvedpn18Oz5ddhrOt86g",
          "Hs64ht9gBSKQ9bpg2755i"
        ],
        "ui": {
          "x": 1199,
          "y": 202,
          "zIndex": 135,
          "widthName": 60,
          "widthComment": 60,
          "color": ""
        },
        "meta": {
          "updateAt": 1729455063814,
          "createAt": 1729454152687
        }
      },
      "fA5YAi6m7r_7Jq-6dO6In": {
        "id": "fA5YAi6m7r_7Jq-6dO6In",
        "name": "Product",
        "comment": "",
        "columnIds": [
          "s1kKAaHAfsX-Hy3zKEq8y",
          "w1MGW3LkqtuZa_BpxGBpK",
          "60_J2_mu4XLfzFhwmHGsc",
          "Y9ach-8NUNLO2Ku3k-ceo",
          "nRYcTpyo4jhnDeESOoqWT",
          "fsZ1k7j2iMg1sb-Dl6Qw0",
          "JwB0jltVllyap5SaFpx3q",
          "iLlwJa71Yt0y1NTH70qHK",
          "eydT_ff0SMhdxLEpRtax8",
          "HQ1k_Y9YVB_yUn4rpo3F8"
        ],
        "seqColumnIds": [
          "s1kKAaHAfsX-Hy3zKEq8y",
          "RMedyOdaXzfoxWfZMBmG1",
          "w1MGW3LkqtuZa_BpxGBpK",
          "60_J2_mu4XLfzFhwmHGsc",
          "Y9ach-8NUNLO2Ku3k-ceo",
          "nRYcTpyo4jhnDeESOoqWT",
          "fsZ1k7j2iMg1sb-Dl6Qw0",
          "JwB0jltVllyap5SaFpx3q",
          "iLlwJa71Yt0y1NTH70qHK",
          "eydT_ff0SMhdxLEpRtax8",
          "HQ1k_Y9YVB_yUn4rpo3F8",
          "QHM9VD8Vmx-CshzI2owFJ"
        ],
        "ui": {
          "x": 707,
          "y": 143,
          "zIndex": 160,
          "widthName": 60,
          "widthComment": 60,
          "color": ""
        },
        "meta": {
          "updateAt": 1729454940282,
          "createAt": 1729454210315
        }
      },
      "wFQyrIndy8OPPc_ww1_zJ": {
        "id": "wFQyrIndy8OPPc_ww1_zJ",
        "name": "Chemical List",
        "comment": "",
        "columnIds": [
          "dgw_1ZAEB-BDWKt9emlxr",
          "3Y67GhqDTXsIjfQ4xu_3p"
        ],
        "seqColumnIds": [
          "EP7YU9AZ5QDCYY2myA1J6",
          "yJwZm9i5uNUM2a1cmko94",
          "TvCjtoz3RAhgvpPDbLaaP",
          "goKPglA9AI7FbdzHtAmFD",
          "dgw_1ZAEB-BDWKt9emlxr",
          "3Y67GhqDTXsIjfQ4xu_3p"
        ],
        "ui": {
          "x": 729,
          "y": 570,
          "zIndex": 262,
          "widthName": 71,
          "widthComment": 60,
          "color": ""
        },
        "meta": {
          "updateAt": 1729456407997,
          "createAt": 1729454439143
        }
      }
    },
    "tableColumnEntities": {
      "4Zxvx0s8Leiigsb9hDuDh": {
        "id": "4Zxvx0s8Leiigsb9hDuDh",
        "tableId": "OHUwIk3akz95xyDa54ouD",
        "name": "CompanyID",
        "comment": "",
        "dataType": "INT",
        "default": "",
        "options": 10,
        "ui": {
          "keys": 1,
          "widthName": 64,
          "widthComment": 60,
          "widthDataType": 60,
          "widthDefault": 60
        },
        "meta": {
          "updateAt": 1729453842168,
          "createAt": 1729453813666
        }
      },
      "nYG4SyWmCAYP5N2vPAz_6": {
        "id": "nYG4SyWmCAYP5N2vPAz_6",
        "tableId": "OHUwIk3akz95xyDa54ouD",
        "name": "Company ID",
        "comment": "",
        "dataType": "INT",
        "default": "",
        "options": 10,
        "ui": {
          "keys": 1,
          "widthName": 67,
          "widthComment": 60,
          "widthDataType": 60,
          "widthDefault": 60
        },
        "meta": {
          "updateAt": 1729454317210,
          "createAt": 1729453853448
        }
      },
      "Ho3945r3JY8Y5r3w2TP2H": {
        "id": "Ho3945r3JY8Y5r3w2TP2H",
        "tableId": "OHUwIk3akz95xyDa54ouD",
        "name": "Company Name",
        "comment": "",
        "dataType": "VARCHAR",
        "default": "",
        "options": 8,
        "ui": {
          "keys": 0,
          "widthName": 88,
          "widthComment": 60,
          "widthDataType": 60,
          "widthDefault": 60
        },
        "meta": {
          "updateAt": 1729453898012,
          "createAt": 1729453868082
        }
      },
      "Lim_plEDkYq8hh62avnjz": {
        "id": "Lim_plEDkYq8hh62avnjz",
        "tableId": "mZHhCYR1X1U1gUz2KWHw5",
        "name": "Brand ID",
        "comment": "",
        "dataType": "INT",
        "default": "",
        "options": 10,
        "ui": {
          "keys": 1,
          "widthName": 60,
          "widthComment": 60,
          "widthDataType": 60,
          "widthDefault": 60
        },
        "meta": {
          "updateAt": 1729454320304,
          "createAt": 1729453916214
        }
      },
      "v8xIZyNHCENlP30ZhysHp": {
        "id": "v8xIZyNHCENlP30ZhysHp",
        "tableId": "mZHhCYR1X1U1gUz2KWHw5",
        "name": "Brand Name",
        "comment": "",
        "dataType": "VARCHAR",
        "default": "",
        "options": 8,
        "ui": {
          "keys": 0,
          "widthName": 68,
          "widthComment": 60,
          "widthDataType": 60,
          "widthDefault": 60
        },
        "meta": {
          "updateAt": 1729454069586,
          "createAt": 1729453929488
        }
      },
      "1ZSgi6DeMk-Jho5R_QizO": {
        "id": "1ZSgi6DeMk-Jho5R_QizO",
        "tableId": "xYQg6fdK8K6X4smH_AEEd",
        "name": "Category ID",
        "comment": "",
        "dataType": "INT",
        "default": "",
        "options": 10,
        "ui": {
          "keys": 1,
          "widthName": 65,
          "widthComment": 60,
          "widthDataType": 60,
          "widthDefault": 60
        },
        "meta": {
          "updateAt": 1729454323282,
          "createAt": 1729453984693
        }
      },
      "8VerGkGgP1UH8UePAsKmT": {
        "id": "8VerGkGgP1UH8UePAsKmT",
        "tableId": "xYQg6fdK8K6X4smH_AEEd",
        "name": "Categroy Name",
        "comment": "",
        "dataType": "VARCHAR",
        "default": "",
        "options": 8,
        "ui": {
          "keys": 0,
          "widthName": 85,
          "widthComment": 60,
          "widthDataType": 60,
          "widthDefault": 60
        },
        "meta": {
          "updateAt": 1729454082558,
          "createAt": 1729454017648
        }
      },
      "kMzuUBPZRJC61024hUJMZ": {
        "id": "kMzuUBPZRJC61024hUJMZ",
        "tableId": "xYQg6fdK8K6X4smH_AEEd",
        "name": "Description",
        "comment": "",
        "dataType": "TEXT",
        "default": "",
        "options": 0,
        "ui": {
          "keys": 0,
          "widthName": 62,
          "widthComment": 60,
          "widthDataType": 60,
          "widthDefault": 60
        },
        "meta": {
          "updateAt": 1729454093640,
          "createAt": 1729454084779
        }
      },
      "MhCRw0EByiT4XV9QFQoTx": {
        "id": "MhCRw0EByiT4XV9QFQoTx",
        "tableId": "HeguguGg0Aurg_X0m8aun",
        "name": "Category ID",
        "comment": "",
        "dataType": "INT",
        "default": "",
        "options": 10,
        "ui": {
          "keys": 1,
          "widthName": 65,
          "widthComment": 60,
          "widthDataType": 60,
          "widthDefault": 60
        },
        "meta": {
          "updateAt": 1729454326263,
          "createAt": 1729454116496
        }
      },
      "5prYfpdXY5jtGTO0sioHA": {
        "id": "5prYfpdXY5jtGTO0sioHA",
        "tableId": "HeguguGg0Aurg_X0m8aun",
        "name": "Category Name",
        "comment": "",
        "dataType": "VARCHAR",
        "default": "",
        "options": 8,
        "ui": {
          "keys": 0,
          "widthName": 85,
          "widthComment": 60,
          "widthDataType": 60,
          "widthDefault": 60
        },
        "meta": {
          "updateAt": 1729454134949,
          "createAt": 1729454116838
        }
      },
      "VCH2_6zYiyzTp7HXJP9Lk": {
        "id": "VCH2_6zYiyzTp7HXJP9Lk",
        "tableId": "HeguguGg0Aurg_X0m8aun",
        "name": "Description",
        "comment": "",
        "dataType": "TEXT",
        "default": "",
        "options": 0,
        "ui": {
          "keys": 0,
          "widthName": 62,
          "widthComment": 60,
          "widthDataType": 60,
          "widthDefault": 60
        },
        "meta": {
          "updateAt": 1729454144477,
          "createAt": 1729454117019
        }
      },
      "ey9Qcpf5S6aTwinQ8-m_j": {
        "id": "ey9Qcpf5S6aTwinQ8-m_j",
        "tableId": "SWR1nBjuriuWRbCNOJ9-8",
        "name": "Chemical ID",
        "comment": "",
        "dataType": "INT",
        "default": "",
        "options": 10,
        "ui": {
          "keys": 1,
          "widthName": 65,
          "widthComment": 60,
          "widthDataType": 60,
          "widthDefault": 60
        },
        "meta": {
          "updateAt": 1729454328532,
          "createAt": 1729454161975
        }
      },
      "LLvedpn18Oz5ddhrOt86g": {
        "id": "LLvedpn18Oz5ddhrOt86g",
        "tableId": "SWR1nBjuriuWRbCNOJ9-8",
        "name": "Chemical Name",
        "comment": "",
        "dataType": "VARCHAR",
        "default": "",
        "options": 8,
        "ui": {
          "keys": 0,
          "widthName": 85,
          "widthComment": 60,
          "widthDataType": 60,
          "widthDefault": 60
        },
        "meta": {
          "updateAt": 1729454193548,
          "createAt": 1729454162128
        }
      },
      "Hs64ht9gBSKQ9bpg2755i": {
        "id": "Hs64ht9gBSKQ9bpg2755i",
        "tableId": "SWR1nBjuriuWRbCNOJ9-8",
        "name": "",
        "comment": "",
        "dataType": "",
        "default": "",
        "options": 0,
        "ui": {
          "keys": 0,
          "widthName": 60,
          "widthComment": 60,
          "widthDataType": 60,
          "widthDefault": 60
        },
        "meta": {
          "updateAt": 1729454162287,
          "createAt": 1729454162287
        }
      },
      "RMedyOdaXzfoxWfZMBmG1": {
        "id": "RMedyOdaXzfoxWfZMBmG1",
        "tableId": "fA5YAi6m7r_7Jq-6dO6In",
        "name": "Product ID",
        "comment": "",
        "dataType": "INT",
        "default": "",
        "options": 10,
        "ui": {
          "keys": 1,
          "widthName": 60,
          "widthComment": 60,
          "widthDataType": 60,
          "widthDefault": 60
        },
        "meta": {
          "updateAt": 1729454330994,
          "createAt": 1729454223653
        }
      },
      "w1MGW3LkqtuZa_BpxGBpK": {
        "id": "w1MGW3LkqtuZa_BpxGBpK",
        "tableId": "fA5YAi6m7r_7Jq-6dO6In",
        "name": "Product Name",
        "comment": "",
        "dataType": "VARCHAR",
        "default": "",
        "options": 8,
        "ui": {
          "keys": 0,
          "widthName": 78,
          "widthComment": 60,
          "widthDataType": 60,
          "widthDefault": 60
        },
        "meta": {
          "updateAt": 1729454246240,
          "createAt": 1729454223817
        }
      },
      "Y9ach-8NUNLO2Ku3k-ceo": {
        "id": "Y9ach-8NUNLO2Ku3k-ceo",
        "tableId": "fA5YAi6m7r_7Jq-6dO6In",
        "name": "Brand ID",
        "comment": "",
        "dataType": "INT",
        "default": "",
        "options": 8,
        "ui": {
          "keys": 0,
          "widthName": 60,
          "widthComment": 60,
          "widthDataType": 60,
          "widthDefault": 60
        },
        "meta": {
          "updateAt": 1729454376650,
          "createAt": 1729454223976
        }
      },
      "nRYcTpyo4jhnDeESOoqWT": {
        "id": "nRYcTpyo4jhnDeESOoqWT",
        "tableId": "fA5YAi6m7r_7Jq-6dO6In",
        "name": "Primary Category ID",
        "comment": "",
        "dataType": "INT",
        "default": "",
        "options": 8,
        "ui": {
          "keys": 0,
          "widthName": 108,
          "widthComment": 60,
          "widthDataType": 60,
          "widthDefault": 60
        },
        "meta": {
          "updateAt": 1729454377207,
          "createAt": 1729454224142
        }
      },
      "fsZ1k7j2iMg1sb-Dl6Qw0": {
        "id": "fsZ1k7j2iMg1sb-Dl6Qw0",
        "tableId": "fA5YAi6m7r_7Jq-6dO6In",
        "name": "Sub Category ID",
        "comment": "",
        "dataType": "INT",
        "default": "",
        "options": 8,
        "ui": {
          "keys": 0,
          "widthName": 88,
          "widthComment": 60,
          "widthDataType": 60,
          "widthDefault": 60
        },
        "meta": {
          "updateAt": 1729454621314,
          "createAt": 1729454224279
        }
      },
      "60_J2_mu4XLfzFhwmHGsc": {
        "id": "60_J2_mu4XLfzFhwmHGsc",
        "tableId": "fA5YAi6m7r_7Jq-6dO6In",
        "name": "Company ID",
        "comment": "",
        "dataType": "INT",
        "default": "",
        "options": 8,
        "ui": {
          "keys": 0,
          "widthName": 67,
          "widthComment": 60,
          "widthDataType": 60,
          "widthDefault": 60
        },
        "meta": {
          "updateAt": 1729454412364,
          "createAt": 1729454400048
        }
      },
      "EP7YU9AZ5QDCYY2myA1J6": {
        "id": "EP7YU9AZ5QDCYY2myA1J6",
        "tableId": "wFQyrIndy8OPPc_ww1_zJ",
        "name": "Product ID",
        "comment": "",
        "dataType": "INT",
        "default": "",
        "options": 8,
        "ui": {
          "keys": 0,
          "widthName": 60,
          "widthComment": 60,
          "widthDataType": 60,
          "widthDefault": 60
        },
        "meta": {
          "updateAt": 1729454466452,
          "createAt": 1729454448633
        }
      },
      "yJwZm9i5uNUM2a1cmko94": {
        "id": "yJwZm9i5uNUM2a1cmko94",
        "tableId": "wFQyrIndy8OPPc_ww1_zJ",
        "name": "Chemical ID",
        "comment": "",
        "dataType": "INT",
        "default": "",
        "options": 8,
        "ui": {
          "keys": 0,
          "widthName": 65,
          "widthComment": 60,
          "widthDataType": 60,
          "widthDefault": 60
        },
        "meta": {
          "updateAt": 1729454477990,
          "createAt": 1729454467645
        }
      },
      "JwB0jltVllyap5SaFpx3q": {
        "id": "JwB0jltVllyap5SaFpx3q",
        "tableId": "fA5YAi6m7r_7Jq-6dO6In",
        "name": "Company ID",
        "comment": "",
        "dataType": "INT",
        "default": "",
        "options": 8,
        "ui": {
          "keys": 2,
          "widthName": 67,
          "widthComment": 60,
          "widthDataType": 60,
          "widthDefault": 60
        },
        "meta": {
          "updateAt": 1729454665127,
          "createAt": 1729454665127
        }
      },
      "iLlwJa71Yt0y1NTH70qHK": {
        "id": "iLlwJa71Yt0y1NTH70qHK",
        "tableId": "fA5YAi6m7r_7Jq-6dO6In",
        "name": "Brand ID",
        "comment": "",
        "dataType": "INT",
        "default": "",
        "options": 8,
        "ui": {
          "keys": 2,
          "widthName": 60,
          "widthComment": 60,
          "widthDataType": 60,
          "widthDefault": 60
        },
        "meta": {
          "updateAt": 1729454690766,
          "createAt": 1729454690766
        }
      },
      "eydT_ff0SMhdxLEpRtax8": {
        "id": "eydT_ff0SMhdxLEpRtax8",
        "tableId": "fA5YAi6m7r_7Jq-6dO6In",
        "name": "Primary Category ID",
        "comment": "",
        "dataType": "INT",
        "default": "",
        "options": 8,
        "ui": {
          "keys": 2,
          "widthName": 108,
          "widthComment": 60,
          "widthDataType": 60,
          "widthDefault": 60
        },
        "meta": {
          "updateAt": 1729455354187,
          "createAt": 1729454749776
        }
      },
      "HQ1k_Y9YVB_yUn4rpo3F8": {
        "id": "HQ1k_Y9YVB_yUn4rpo3F8",
        "tableId": "fA5YAi6m7r_7Jq-6dO6In",
        "name": "Sub Category ID",
        "comment": "",
        "dataType": "INT",
        "default": "",
        "options": 8,
        "ui": {
          "keys": 2,
          "widthName": 88,
          "widthComment": 60,
          "widthDataType": 60,
          "widthDefault": 60
        },
        "meta": {
          "updateAt": 1729455340058,
          "createAt": 1729454760539
        }
      },
      "TvCjtoz3RAhgvpPDbLaaP": {
        "id": "TvCjtoz3RAhgvpPDbLaaP",
        "tableId": "wFQyrIndy8OPPc_ww1_zJ",
        "name": "",
        "comment": "",
        "dataType": "",
        "default": "",
        "options": 10,
        "ui": {
          "keys": 1,
          "widthName": 60,
          "widthComment": 60,
          "widthDataType": 60,
          "widthDefault": 60
        },
        "meta": {
          "updateAt": 1729454792245,
          "createAt": 1729454792245
        }
      },
      "QHM9VD8Vmx-CshzI2owFJ": {
        "id": "QHM9VD8Vmx-CshzI2owFJ",
        "tableId": "fA5YAi6m7r_7Jq-6dO6In",
        "name": "",
        "comment": "",
        "dataType": "",
        "default": "",
        "options": 8,
        "ui": {
          "keys": 0,
          "widthName": 60,
          "widthComment": 60,
          "widthDataType": 60,
          "widthDefault": 60
        },
        "meta": {
          "updateAt": 1729454793629,
          "createAt": 1729454793629
        }
      },
      "goKPglA9AI7FbdzHtAmFD": {
        "id": "goKPglA9AI7FbdzHtAmFD",
        "tableId": "wFQyrIndy8OPPc_ww1_zJ",
        "name": "Product ID",
        "comment": "",
        "dataType": "INT",
        "default": "",
        "options": 10,
        "ui": {
          "keys": 1,
          "widthName": 60,
          "widthComment": 60,
          "widthDataType": 60,
          "widthDefault": 60
        },
        "meta": {
          "updateAt": 1729454874052,
          "createAt": 1729454814560
        }
      },
      "s1kKAaHAfsX-Hy3zKEq8y": {
        "id": "s1kKAaHAfsX-Hy3zKEq8y",
        "tableId": "fA5YAi6m7r_7Jq-6dO6In",
        "name": "Product ID",
        "comment": "",
        "dataType": "INT",
        "default": "",
        "options": 10,
        "ui": {
          "keys": 1,
          "widthName": 60,
          "widthComment": 60,
          "widthDataType": 60,
          "widthDefault": 60
        },
        "meta": {
          "updateAt": 1729454839627,
          "createAt": 1729454816192
        }
      },
      "3ODW-TsDOXhFcTLejp6qx": {
        "id": "3ODW-TsDOXhFcTLejp6qx",
        "tableId": "SWR1nBjuriuWRbCNOJ9-8",
        "name": "Chemical ID",
        "comment": "",
        "dataType": "INT",
        "default": "",
        "options": 10,
        "ui": {
          "keys": 1,
          "widthName": 65,
          "widthComment": 60,
          "widthDataType": 60,
          "widthDefault": 60
        },
        "meta": {
          "updateAt": 1729454886709,
          "createAt": 1729454864835
        }
      },
      "3Y67GhqDTXsIjfQ4xu_3p": {
        "id": "3Y67GhqDTXsIjfQ4xu_3p",
        "tableId": "wFQyrIndy8OPPc_ww1_zJ",
        "name": "Chemical ID",
        "comment": "",
        "dataType": "INT",
        "default": "",
        "options": 10,
        "ui": {
          "keys": 3,
          "widthName": 65,
          "widthComment": 60,
          "widthDataType": 60,
          "widthDefault": 60
        },
        "meta": {
          "updateAt": 1729455774614,
          "createAt": 1729454867117
        }
      },
      "dgw_1ZAEB-BDWKt9emlxr": {
        "id": "dgw_1ZAEB-BDWKt9emlxr",
        "tableId": "wFQyrIndy8OPPc_ww1_zJ",
        "name": "Product ID",
        "comment": "",
        "dataType": "INT",
        "default": "",
        "options": 10,
        "ui": {
          "keys": 3,
          "widthName": 60,
          "widthComment": 60,
          "widthDataType": 60,
          "widthDefault": 60
        },
        "meta": {
          "updateAt": 1729455770212,
          "createAt": 1729455003785
        }
      }
    },
    "relationshipEntities": {
      "HrhjzYRmn4BteqTXRRN6U": {
        "id": "HrhjzYRmn4BteqTXRRN6U",
        "identification": false,
        "relationshipType": 16,
        "startRelationshipType": 2,
        "start": {
          "tableId": "OHUwIk3akz95xyDa54ouD",
          "columnIds": [
            "nYG4SyWmCAYP5N2vPAz_6"
          ],
          "x": 396,
          "y": 182,
          "direction": 2
        },
        "end": {
          "tableId": "fA5YAi6m7r_7Jq-6dO6In",
          "columnIds": [
            "JwB0jltVllyap5SaFpx3q"
          ],
          "x": 707,
          "y": 180,
          "direction": 1
        },
        "meta": {
          "updateAt": 1729454665127,
          "createAt": 1729454665127
        }
      },
      "D4k-smELvxhynQASujH8f": {
        "id": "D4k-smELvxhynQASujH8f",
        "identification": false,
        "relationshipType": 16,
        "startRelationshipType": 2,
        "start": {
          "tableId": "mZHhCYR1X1U1gUz2KWHw5",
          "columnIds": [
            "Lim_plEDkYq8hh62avnjz"
          ],
          "x": 376,
          "y": 294,
          "direction": 2
        },
        "end": {
          "tableId": "fA5YAi6m7r_7Jq-6dO6In",
          "columnIds": [
            "iLlwJa71Yt0y1NTH70qHK"
          ],
          "x": 707,
          "y": 254,
          "direction": 1
        },
        "meta": {
          "updateAt": 1729454690766,
          "createAt": 1729454690766
        }
      },
      "esEsOG2cEPwgDGCr8Ocl-": {
        "id": "esEsOG2cEPwgDGCr8Ocl-",
        "identification": false,
        "relationshipType": 16,
        "startRelationshipType": 2,
        "start": {
          "tableId": "xYQg6fdK8K6X4smH_AEEd",
          "columnIds": [
            "1ZSgi6DeMk-Jho5R_QizO"
          ],
          "x": 394,
          "y": 415,
          "direction": 2
        },
        "end": {
          "tableId": "fA5YAi6m7r_7Jq-6dO6In",
          "columnIds": [
            "eydT_ff0SMhdxLEpRtax8"
          ],
          "x": 707,
          "y": 328,
          "direction": 1
        },
        "meta": {
          "updateAt": 1729454749776,
          "createAt": 1729454749776
        }
      },
      "fUM9GdfcLQrUJvGxaCIe3": {
        "id": "fUM9GdfcLQrUJvGxaCIe3",
        "identification": false,
        "relationshipType": 16,
        "startRelationshipType": 2,
        "start": {
          "tableId": "HeguguGg0Aurg_X0m8aun",
          "columnIds": [
            "MhCRw0EByiT4XV9QFQoTx"
          ],
          "x": 395,
          "y": 549,
          "direction": 2
        },
        "end": {
          "tableId": "fA5YAi6m7r_7Jq-6dO6In",
          "columnIds": [
            "HQ1k_Y9YVB_yUn4rpo3F8"
          ],
          "x": 707,
          "y": 402,
          "direction": 1
        },
        "meta": {
          "updateAt": 1729454760539,
          "createAt": 1729454760539
        }
      },
      "TIpObuk1kZP4yLtMeCByk": {
        "id": "TIpObuk1kZP4yLtMeCByk",
        "identification": false,
        "relationshipType": 16,
        "startRelationshipType": 2,
        "start": {
          "tableId": "wFQyrIndy8OPPc_ww1_zJ",
          "columnIds": [
            "TvCjtoz3RAhgvpPDbLaaP"
          ],
          "x": 1134,
          "y": 255,
          "direction": 1
        },
        "end": {
          "tableId": "fA5YAi6m7r_7Jq-6dO6In",
          "columnIds": [
            "QHM9VD8Vmx-CshzI2owFJ"
          ],
          "x": 1041,
          "y": 392,
          "direction": 2
        },
        "meta": {
          "updateAt": 1729454793629,
          "createAt": 1729454793629
        }
      },
      "KHTTvsEw-3eX-2iUEGPq3": {
        "id": "KHTTvsEw-3eX-2iUEGPq3",
        "identification": true,
        "relationshipType": 16,
        "startRelationshipType": 2,
        "start": {
          "tableId": "wFQyrIndy8OPPc_ww1_zJ",
          "columnIds": [
            "goKPglA9AI7FbdzHtAmFD"
          ],
          "x": 967,
          "y": 628,
          "direction": 1
        },
        "end": {
          "tableId": "fA5YAi6m7r_7Jq-6dO6In",
          "columnIds": [
            "s1kKAaHAfsX-Hy3zKEq8y"
          ],
          "x": 913.5,
          "y": 439,
          "direction": 8
        },
        "meta": {
          "updateAt": 1729454816192,
          "createAt": 1729454816192
        }
      },
      "t0DA6SoiX-EPclq0fFaVW": {
        "id": "t0DA6SoiX-EPclq0fFaVW",
        "identification": true,
        "relationshipType": 16,
        "startRelationshipType": 2,
        "start": {
          "tableId": "SWR1nBjuriuWRbCNOJ9-8",
          "columnIds": [
            "3ODW-TsDOXhFcTLejp6qx"
          ],
          "x": 1199,
          "y": 254,
          "direction": 1
        },
        "end": {
          "tableId": "wFQyrIndy8OPPc_ww1_zJ",
          "columnIds": [
            "3Y67GhqDTXsIjfQ4xu_3p"
          ],
          "x": 1099,
          "y": 622,
          "direction": 2
        },
        "meta": {
          "updateAt": 1729454867117,
          "createAt": 1729454867117
        }
      },
      "JIumuo9Fx7Ba-cwTTJRq7": {
        "id": "JIumuo9Fx7Ba-cwTTJRq7",
        "identification": true,
        "relationshipType": 16,
        "startRelationshipType": 2,
        "start": {
          "tableId": "fA5YAi6m7r_7Jq-6dO6In",
          "columnIds": [
            "s1kKAaHAfsX-Hy3zKEq8y"
          ],
          "x": 913.5,
          "y": 439,
          "direction": 8
        },
        "end": {
          "tableId": "wFQyrIndy8OPPc_ww1_zJ",
          "columnIds": [
            "dgw_1ZAEB-BDWKt9emlxr"
          ],
          "x": 914,
          "y": 570,
          "direction": 4
        },
        "meta": {
          "updateAt": 1729455003785,
          "createAt": 1729455003785
        }
      }
    },
    "indexEntities": {
      "Fc4RFENcmgBXlYrL0Bdxc": {
        "id": "Fc4RFENcmgBXlYrL0Bdxc",
        "name": "",
        "tableId": "wFQyrIndy8OPPc_ww1_zJ",
        "indexColumnIds": [],
        "seqIndexColumnIds": [],
        "unique": false,
        "meta": {
          "updateAt": 1729455680473,
          "createAt": 1729455680473
        }
      },
      "Cq6dS0_fBam3XtsSnMZqt": {
        "id": "Cq6dS0_fBam3XtsSnMZqt",
        "name": "",
        "tableId": "wFQyrIndy8OPPc_ww1_zJ",
        "indexColumnIds": [],
        "seqIndexColumnIds": [],
        "unique": true,
        "meta": {
          "updateAt": 1729455684947,
          "createAt": 1729455681781
        }
      }
    },
    "indexColumnEntities": {},
    "memoEntities": {}
  },
  "lww": {
    "OHUwIk3akz95xyDa54ouD": [
      "tableEntities",
      1729453796995,
      -1,
      {
        "name": 1729453823053
      }
    ],
    "4Zxvx0s8Leiigsb9hDuDh": [
      "tableColumnEntities",
      1729453813665,
      1729453851372,
      {
        "options(primaryKey)": 1729453829958,
        "name": 1729453836841,
        "dataType": 1729453842168
      }
    ],
    "nYG4SyWmCAYP5N2vPAz_6": [
      "tableColumnEntities",
      1729453853448,
      -1,
      {
        "options(primaryKey)": 1729453855325,
        "name": 1729454317210,
        "dataType": 1729453866123
      }
    ],
    "Ho3945r3JY8Y5r3w2TP2H": [
      "tableColumnEntities",
      1729453868082,
      -1,
      {
        "name": 1729453872179,
        "dataType": 1729453895772,
        "options(notNull)": 1729453898011
      }
    ],
    "mZHhCYR1X1U1gUz2KWHw5": [
      "tableEntities",
      1729453905772,
      -1,
      {
        "name": 1729453914489,
        "ui.color": 1729454720303
      }
    ],
    "Lim_plEDkYq8hh62avnjz": [
      "tableColumnEntities",
      1729453916214,
      -1,
      {
        "options(primaryKey)": 1729453917713,
        "name": 1729454320302,
        "dataType": 1729453928063
      }
    ],
    "v8xIZyNHCENlP30ZhysHp": [
      "tableColumnEntities",
      1729453929488,
      -1,
      {
        "name": 1729453933434,
        "dataType": 1729453936936,
        "options(notNull)": 1729454069586
      }
    ],
    "xYQg6fdK8K6X4smH_AEEd": [
      "tableEntities",
      1729453944353,
      -1,
      {
        "name": 1729453952653
      }
    ],
    "1ZSgi6DeMk-Jho5R_QizO": [
      "tableColumnEntities",
      1729453984693,
      -1,
      {
        "name": 1729454323282,
        "options(primaryKey)": 1729454011624,
        "dataType": 1729454016566
      }
    ],
    "8VerGkGgP1UH8UePAsKmT": [
      "tableColumnEntities",
      1729454017648,
      -1,
      {
        "name": 1729454059121,
        "options(notNull)": 1729454067949,
        "dataType": 1729454082558
      }
    ],
    "kMzuUBPZRJC61024hUJMZ": [
      "tableColumnEntities",
      1729454084778,
      -1,
      {
        "name": 1729454089969,
        "dataType": 1729454093639
      }
    ],
    "HeguguGg0Aurg_X0m8aun": [
      "tableEntities",
      1729454099542,
      -1,
      {
        "name": 1729454615713
      }
    ],
    "MhCRw0EByiT4XV9QFQoTx": [
      "tableColumnEntities",
      1729454116495,
      -1,
      {
        "name": 1729454326262,
        "options(primaryKey)": 1729454123103,
        "dataType": 1729454126836
      }
    ],
    "5prYfpdXY5jtGTO0sioHA": [
      "tableColumnEntities",
      1729454116837,
      -1,
      {
        "name": 1729454130627,
        "dataType": 1729454133156,
        "options(notNull)": 1729454134949
      }
    ],
    "VCH2_6zYiyzTp7HXJP9Lk": [
      "tableColumnEntities",
      1729454117018,
      -1,
      {
        "name": 1729454140114,
        "dataType": 1729454144476
      }
    ],
    "SWR1nBjuriuWRbCNOJ9-8": [
      "tableEntities",
      1729454152687,
      -1,
      {
        "name": 1729454160285
      }
    ],
    "ey9Qcpf5S6aTwinQ8-m_j": [
      "tableColumnEntities",
      1729454161975,
      1729454855083,
      {
        "name": 1729454328531,
        "options(primaryKey)": 1729454169353,
        "dataType": 1729454172074,
        "default": 1729454179922
      }
    ],
    "LLvedpn18Oz5ddhrOt86g": [
      "tableColumnEntities",
      1729454162127,
      -1,
      {
        "name": 1729454189190,
        "dataType": 1729454192221,
        "options(notNull)": 1729454193548
      }
    ],
    "Hs64ht9gBSKQ9bpg2755i": [
      "tableColumnEntities",
      1729454162287,
      1729454200719,
      {}
    ],
    "fA5YAi6m7r_7Jq-6dO6In": [
      "tableEntities",
      1729454210314,
      -1,
      {
        "name": 1729454221837,
        "ui.color": 1729454703999
      }
    ],
    "RMedyOdaXzfoxWfZMBmG1": [
      "tableColumnEntities",
      1729454223653,
      1729454831146,
      {
        "name": 1729454330993,
        "options(primaryKey)": 1729454231927,
        "dataType": 1729454234488
      }
    ],
    "w1MGW3LkqtuZa_BpxGBpK": [
      "tableColumnEntities",
      1729454223816,
      -1,
      {
        "name": 1729454241411,
        "dataType": 1729454245094,
        "options(notNull)": 1729454246240
      }
    ],
    "Y9ach-8NUNLO2Ku3k-ceo": [
      "tableColumnEntities",
      1729454223976,
      -1,
      {
        "name": 1729454333451,
        "dataType": 1729454370800,
        "options(notNull)": 1729454376650
      }
    ],
    "nRYcTpyo4jhnDeESOoqWT": [
      "tableColumnEntities",
      1729454224141,
      -1,
      {
        "name": 1729454341569,
        "dataType": 1729454364922,
        "options(notNull)": 1729454377207
      }
    ],
    "fsZ1k7j2iMg1sb-Dl6Qw0": [
      "tableColumnEntities",
      1729454224278,
      -1,
      {
        "name": 1729454621314,
        "dataType": 1729454367863,
        "options(notNull)": 1729454377805
      }
    ],
    "60_J2_mu4XLfzFhwmHGsc": [
      "tableColumnEntities",
      1729454400047,
      -1,
      {
        "name": 1729454406106,
        "dataType": 1729454411489,
        "options(notNull)": 1729454412364
      }
    ],
    "wFQyrIndy8OPPc_ww1_zJ": [
      "tableEntities",
      1729454439142,
      -1,
      {
        "name": 1729454446578
      }
    ],
    "EP7YU9AZ5QDCYY2myA1J6": [
      "tableColumnEntities",
      1729454448632,
      1729454850497,
      {
        "name": 1729454461332,
        "dataType": 1729454465709,
        "options(notNull)": 1729454466452
      }
    ],
    "yJwZm9i5uNUM2a1cmko94": [
      "tableColumnEntities",
      1729454467644,
      1729454853796,
      {
        "name": 1729454472693,
        "dataType": 1729454476708,
        "options(notNull)": 1729454477990
      }
    ],
    "JwB0jltVllyap5SaFpx3q": [
      "tableColumnEntities",
      1729454665125,
      -1,
      {
        "options(notNull)": 1729454665125,
        "name": 1729454665125,
        "dataType": 1729454665125,
        "default": 1729454665125,
        "comment": 1729454665125
      }
    ],
    "HrhjzYRmn4BteqTXRRN6U": [
      "relationshipEntities",
      1729454665125,
      -1,
      {}
    ],
    "iLlwJa71Yt0y1NTH70qHK": [
      "tableColumnEntities",
      1729454690765,
      -1,
      {
        "options(notNull)": 1729454690765,
        "name": 1729454690765,
        "dataType": 1729454690765,
        "default": 1729454690765,
        "comment": 1729454690765
      }
    ],
    "D4k-smELvxhynQASujH8f": [
      "relationshipEntities",
      1729454690765,
      -1,
      {}
    ],
    "eydT_ff0SMhdxLEpRtax8": [
      "tableColumnEntities",
      1729454749774,
      -1,
      {
        "options(notNull)": 1729454749774,
        "name": 1729455354186,
        "dataType": 1729454749774,
        "default": 1729454749774,
        "comment": 1729454749774
      }
    ],
    "esEsOG2cEPwgDGCr8Ocl-": [
      "relationshipEntities",
      1729454749774,
      -1,
      {}
    ],
    "HQ1k_Y9YVB_yUn4rpo3F8": [
      "tableColumnEntities",
      1729454760539,
      -1,
      {
        "options(notNull)": 1729454760539,
        "name": 1729455340058,
        "dataType": 1729454760539,
        "default": 1729454760539,
        "comment": 1729454760539
      }
    ],
    "fUM9GdfcLQrUJvGxaCIe3": [
      "relationshipEntities",
      1729454760539,
      -1,
      {}
    ],
    "TvCjtoz3RAhgvpPDbLaaP": [
      "tableColumnEntities",
      1729454792240,
      1729454802566,
      {
        "options(primaryKey)": 1729454792240
      }
    ],
    "QHM9VD8Vmx-CshzI2owFJ": [
      "tableColumnEntities",
      1729454793628,
      1729454799510,
      {
        "options(notNull)": 1729454793628,
        "name": 1729454793628,
        "dataType": 1729454793628,
        "default": 1729454793628,
        "comment": 1729454793628
      }
    ],
    "TIpObuk1kZP4yLtMeCByk": [
      "relationshipEntities",
      1729454793628,
      1729454799510,
      {}
    ],
    "goKPglA9AI7FbdzHtAmFD": [
      "tableColumnEntities",
      1729454814560,
      1729455008557,
      {
        "options(primaryKey)": 1729454874052,
        "dataType": 1729454839626,
        "name": 1729454847862
      }
    ],
    "s1kKAaHAfsX-Hy3zKEq8y": [
      "tableColumnEntities",
      1729454816191,
      -1,
      {
        "options(notNull)": 1729454816191,
        "name": 1729454827989,
        "dataType": 1729454839626,
        "default": 1729454816191,
        "comment": 1729454816191,
        "options(primaryKey)": 1729454834915
      }
    ],
    "KHTTvsEw-3eX-2iUEGPq3": [
      "relationshipEntities",
      1729454816191,
      1729454991024,
      {}
    ],
    "3ODW-TsDOXhFcTLejp6qx": [
      "tableColumnEntities",
      1729454864834,
      -1,
      {
        "options(primaryKey)": 1729454864834,
        "name": 1729454883187,
        "dataType": 1729454886709
      }
    ],
    "3Y67GhqDTXsIjfQ4xu_3p": [
      "tableColumnEntities",
      1729454867116,
      -1,
      {
        "options(notNull)": 1729454867116,
        "name": 1729454892419,
        "dataType": 1729454886709,
        "default": 1729454867116,
        "comment": 1729454867116,
        "options(primaryKey)": 1729455774614
      }
    ],
    "t0DA6SoiX-EPclq0fFaVW": [
      "relationshipEntities",
      1729454867116,
      -1,
      {}
    ],
    "dgw_1ZAEB-BDWKt9emlxr": [
      "tableColumnEntities",
      1729455003783,
      -1,
      {
        "options(notNull)": 1729455003783,
        "name": 1729455003783,
        "dataType": 1729455003783,
        "default": 1729455003783,
        "comment": 1729455003783,
        "options(primaryKey)": 1729455770212
      }
    ],
    "JIumuo9Fx7Ba-cwTTJRq7": [
      "relationshipEntities",
      1729455003783,
      -1,
      {}
    ],
    "Fc4RFENcmgBXlYrL0Bdxc": [
      "indexEntities",
      1729455680472,
      1729455682912,
      {}
    ],
    "Cq6dS0_fBam3XtsSnMZqt": [
      "indexEntities",
      1729455681781,
      1729455687849,
      {
        "unique": 1729455684946
      }
    ]
  }
}